visjs_component/__init__.py
visjs_component/frontend/index.html
visjs_component/frontend/main.js
visjs_component/frontend/streamlit-component-lib.js
visjs_component/frontend/style.css
visjs_component-0.2.0.dist-info/LICENSE
visjs_component-0.2.0.dist-info/METADATA
visjs_component-0.2.0.dist-info/WHEEL
visjs_component-0.2.0.dist-info/top_level.txt
visjs_component-0.2.0.dist-info/RECORD
