Metadata-Version: 2.1
Name: visjs-component
Version: 0.2.0
Summary: Streamlit component that wraps visjs
Author: yupikaiei
Author-email: xtremerhd@gmail.com
Requires-Python: >=3.7
License-File: LICENSE
Requires-Dist: streamlit >=1.2
Requires-Dist: jinja2
